{
  "slide_id": "bcg_how-cpg-retail-leaders-maximize-ai-roi_slide_010",
  "image_path": "slides/bcg_how-cpg-retail-leaders-maximize-ai-roi_slide_010.png",
  "dimensions": {
    "width": 1241,
    "height": 1754
  },
  "source_company": "BCG",
  "label": {
    "slide_filename": "bcg_how-cpg-retail-leaders-maximize-ai-roi_slide_010.png",
    "layout_type": "mixed_layout",
    "chart_type": "mixed",
    "text_density": "medium",
    "has_icons_illustrations": true,
    "has_data_callouts": true,
    "column_count": 2,
    "color_palette": {
      "primary_accent": "#8FDBC3",
      "background": "#FAFAFA"
    },
    "headline_present": true,
    "source_company": "BCG",
    "slide_purpose": "framing_context",
    "estimated_quality_score": 4
  },
  "fidelity": {
    "regions": {
      "left_rail": null,
      "vertical_divider": null,
      "title_region": {
        "x": 0.05,
        "y": 0.0599,
        "w": 0.8695,
        "h": 0.0274
      },
      "subtitle_region": {
        "x": 0.05,
        "y": 0.0861,
        "w": 0.8695,
        "h": 0.0234
      },
      "main_content_region": {
        "x": 0.0717,
        "y": 0.122,
        "w": 0.8276,
        "h": 0.7035
      },
      "right_panel": null,
      "footer_region": {
        "x": 0.0395,
        "y": 0.8563,
        "w": 0.9605,
        "h": 0.1123
      }
    },
    "chart_region": {
      "x": 0.0717,
      "y": 0.122,
      "w": 0.8276,
      "h": 0.7035
    },
    "has_left_nav_rail": false,
    "has_right_insight_panel": false,
    "has_footer": true,
    "whitespace_share": 0.9088,
    "dominant_palette": [
      {
        "hex": "#F0F0F0",
        "share": 0.9098
      },
      {
        "hex": "#001800",
        "share": 0.0176
      },
      {
        "hex": "#D8D8D8",
        "share": 0.0076
      },
      {
        "hex": "#C0C0C0",
        "share": 0.0054
      },
      {
        "hex": "#304830",
        "share": 0.0045
      },
      {
        "hex": "#183018",
        "share": 0.0042
      },
      {
        "hex": "#A8A8A8",
        "share": 0.0039
      },
      {
        "hex": "#607860",
        "share": 0.0037
      }
    ],
    "color_tokens": {
      "background": "#F0F0F0",
      "rail": null,
      "divider": null,
      "panel": null,
      "accent": "#001800",
      "text_primary": "#0C2B15"
    },
    "layout_dims": {
      "content_x": 0.0,
      "title_y": 0.0599,
      "title_h": 0.0274,
      "subtitle_y": 0.0861,
      "subtitle_h": 0.0234,
      "content_y": 0.122,
      "content_w": 0.8276,
      "content_h": 0.7035,
      "content_x_end": 0.8993,
      "footer_y": 0.8563,
      "footer_h": 0.1123
    },
    "text_density": {
      "ink_fraction": 0.0724,
      "category": "high"
    },
    "design_recipe": "title_stack + mixed_chart_field",
    "style_anchor_score": 2.9
  }
}