{
  "slide_id": "worldbank_Charting_the_Course_A_Water_Security_Diagnosti_slide_005",
  "image_path": "slides/worldbank_Charting_the_Course_A_Water_Security_Diagnosti_slide_005.png",
  "dimensions": {
    "width": 1241,
    "height": 1754
  },
  "source_company": "World Bank",
  "label": {
    "slide_filename": "worldbank_Charting_the_Course_A_Water_Security_Diagnosti_slide_005.png",
    "layout_type": "two_col_chart",
    "chart_type": "mixed",
    "text_density": "medium",
    "has_icons_illustrations": false,
    "has_data_callouts": true,
    "column_count": 2,
    "color_palette": {
      "primary_accent": "#6FB8BE",
      "background": "#FCFCFC"
    },
    "headline_present": true,
    "source_company": "World Bank",
    "slide_purpose": "data_evidence",
    "estimated_quality_score": 3
  },
  "fidelity": {
    "regions": {
      "left_rail": null,
      "vertical_divider": null,
      "title_region": {
        "x": 0.05,
        "y": 0.0724,
        "w": 0.8695,
        "h": 0.0177
      },
      "subtitle_region": {
        "x": 0.05,
        "y": 0.0912,
        "w": 0.8695,
        "h": 0.0177
      },
      "main_content_region": {
        "x": 0.0951,
        "y": 0.1249,
        "w": 0.8042,
        "h": 0.5507
      },
      "right_panel": null,
      "footer_region": {
        "x": 0.0395,
        "y": 0.943,
        "w": 0.9605,
        "h": 0.0097
      }
    },
    "chart_region": {
      "x": 0.0951,
      "y": 0.1249,
      "w": 0.8042,
      "h": 0.5507
    },
    "has_left_nav_rail": false,
    "has_right_insight_panel": false,
    "has_footer": true,
    "whitespace_share": 0.9383,
    "dominant_palette": [
      {
        "hex": "#F0F0F0",
        "share": 0.939
      },
      {
        "hex": "#000000",
        "share": 0.0275
      },
      {
        "hex": "#181818",
        "share": 0.0044
      },
      {
        "hex": "#D8D8D8",
        "share": 0.0044
      },
      {
        "hex": "#303030",
        "share": 0.0041
      },
      {
        "hex": "#484848",
        "share": 0.0038
      },
      {
        "hex": "#A8A8A8",
        "share": 0.0037
      },
      {
        "hex": "#C0C0C0",
        "share": 0.0035
      }
    ],
    "color_tokens": {
      "background": "#F0F0F0",
      "rail": null,
      "divider": null,
      "panel": null,
      "accent": null,
      "text_primary": "#000000"
    },
    "layout_dims": {
      "content_x": 0.0,
      "title_y": 0.0724,
      "title_h": 0.0177,
      "subtitle_y": 0.0912,
      "subtitle_h": 0.0177,
      "content_y": 0.1249,
      "content_w": 0.8042,
      "content_h": 0.5507,
      "content_x_end": 0.8993,
      "footer_y": 0.943,
      "footer_h": 0.0097
    },
    "text_density": {
      "ink_fraction": 0.086,
      "category": "high"
    },
    "design_recipe": "title_stack + mixed_chart_field",
    "style_anchor_score": 0.9
  }
}