{
  "description": "Create a content slide titled 'A Portrait of the Future' with a two-column narrative text layout and a right-side illustrative image panel about AI-enabled fashion design and customer personas.",
  "spec": {
    "slide_type": "content",
    "header": {
      "kicker": "Technology Vision 2025 | AI: A Declaration of Autonomy",
      "headline": "A Portrait of the Future",
      "sub": "The New Learning Loop"
    },
    "layout": "sidebar-right",
    "content": {
      "main": {
        "type": "text-block",
        "title": "",
        "body": "Sam is creative director at BlueDot Apparel—a sustainable fashion brand—and her team is gearing up to start next year’s product line. She kicks off the season with a challenge: “Ask for any AI tool you need; Use them how you want. But give me designs I’ve never seen before.”\n\nHer designers jump in. They’re fresh from a generative AI training program, where they spent two weeks learning fundamentals and experimenting with design automation tools. They’re ready to test their ideas.\n\nSome use a mood board copilot to inspire their creativity. The copilot follows what the designers’ put on their boards, finds similar images, suggests color palettes, and even generates designs to help them get started. Others begin with hand drawing. For them, imagining something new is the best part. But they’re still using AI assistants, tuned on material characteristics, to help pick the right fabrics and construction techniques.\n\nAnd one designer is trying something very different. He requested a tabletop weaving machine and image-to-CAD tool that can turn 2D images into real-world 3D prototypes in under an hour. He’s hoping the chance to physically test more options will give him the freedom to be bolder in his designs.\n\nSam is thrilled to see the energy. She thinks they’ll deliver the company’s most innovative ideas yet. And she has her own AI experiment underway too. She’s working with a startup to create hundreds of virtual AI personas of their customers, which will give feedback on their products before they’re actually released. Then, with this feedback and her own expertise, she’ll evaluate her designers’ work, making final selections with the likeliest chance of success."
      },
      "sidebar": {
        "type": "text-block",
        "title": "Illustration",
        "body": "Abstract fashion figure illustration representing the future of AI-enabled apparel design."
      }
    },
    "footer": {
      "source": "",
      "page": 58
    }
  }
}