{
  "description": "Create a content slide titled Affordable joy with a two-column text layout and a left-side supporting image, covering how consumers seek low-cost joy through piracy, dupes, and counterfeit consumption.",
  "spec": {
    "slide_type": "content",
    "header": {
      "kicker": "",
      "headline": "Affordable joy",
      "sub": ""
    },
    "layout": "sidebar-left",
    "content": {
      "sidebar": {
        "type": "text-block",
        "title": "",
        "body": "Supporting image"
      },
      "main": {
        "type": "text-block",
        "title": "",
        "body": "Once the bills are paid, people derive joy from the extras in life, whether that means aspirational fashion items, memorable experiences or escapism entertainment. Faced with economic pressures, many are seeing their “fun money” depleting, and some are turning to questionable or even illegal ways to find joy.\n\nFor instance, a trend dubbed “pirate and chill” is surging, costing the US economy billions. People are streaming content they haven’t paid for, and/or accessing streaming services that aren’t officially available in their country. According to Forbes Advisor 2024, illegal streaming is surging around the world, and 46% of people with VPN access use it for streaming services. A VPN has the added benefit of reducing the cost of accessing the service, and in many cases, the illicit services are almost as easy to use as the paid-for ones. In 2024, around 20 million viewers illegally streamed a key boxing match between Tyson Fury and Oleksandr Ysuk, costing pay-per-view broadcasters an estimated GBP95 million in profits.\n\nIn fashion and beauty, counterfeits and dupes have become popular among Gen Z and Millennials, enabling them to enjoy the style without the price tag. The shift here is that while wearing a fake luxury watch or branded clothing was once something to hide and pass off as real, wearing a dupe is now accepted as a smart way to embrace a style affordably. With rising demand comes accelerating production, and the cycle drives itself—with some help from social media. Certain online retailers have become known for their habit of copying items on the luxury market. The difference is that now, they’re also targeting the work of independent designers, to poorer quality standards, which is seriously impacting small businesses’ profits."
      }
    },
    "footer": {
      "source": "Accenture Life Trends 2025",
      "page": 45
    }
  }
}