{
  "description": "Create an authors slide in a two-column layout with a featured author profile on the left and contributor lists on the right.",
  "spec": {
    "slide_type": "content",
    "header": {
      "kicker": "Technology Vision 2025 | AI: A Declaration of Autonomy",
      "headline": "Authors",
      "sub": ""
    },
    "layout": "two-column",
    "content": {
      "left": {
        "type": "bullet-list",
        "title": "Karthik Narain\nGroup Chief Executive of Technology and CTO\nLinkedIn\n\nTechnology Vision 2025 Editorial & Research Team",
        "items": [
          {
            "text": "Ari Bernstein",
            "sub": ""
          },
          {
            "text": "Rebecca Kelliher",
            "sub": ""
          },
          {
            "text": "Naomi Nishihara",
            "sub": ""
          },
          {
            "text": "David Strachan-Olson",
            "sub": ""
          }
        ]
      },
      "right": {
        "type": "bullet-list",
        "title": "Accenture Research",
        "items": [
          {
            "text": "Prashant P. Shukla, PhD",
            "sub": ""
          },
          {
            "text": "Renee Byrnes",
            "sub": ""
          },
          {
            "text": "Abira Sathiyanathan",
            "sub": ""
          },
          {
            "text": "Donovan Griggs",
            "sub": ""
          },
          {
            "text": "Gerry Farkova",
            "sub": ""
          },
          {
            "text": "Lohith Kumar",
            "sub": ""
          },
          {
            "text": "Rohan Girish Amrute",
            "sub": ""
          },
          {
            "text": "Mariusz Bidelski",
            "sub": ""
          },
          {
            "text": "Gargi Chakrabarty",
            "sub": ""
          },
          {
            "text": "Abhishek Gupta",
            "sub": ""
          },
          {
            "text": "Kevin Gallagher",
            "sub": ""
          },
          {
            "text": "Carrie Kleiner",
            "sub": ""
          },
          {
            "text": "Paul D. Johnson",
            "sub": ""
          },
          {
            "text": "Ignacio Mamone",
            "sub": ""
          },
          {
            "text": "Anna Marszalik",
            "sub": ""
          },
          {
            "text": "Abhishek Kumar Mishra",
            "sub": ""
          },
          {
            "text": "Sandra Najem",
            "sub": ""
          },
          {
            "text": "Vincenzo Palermo",
            "sub": ""
          },
          {
            "text": "Shruti Panda",
            "sub": ""
          },
          {
            "text": "Linda Ringnalda",
            "sub": ""
          },
          {
            "text": "Shruti Shalini",
            "sub": ""
          },
          {
            "text": "Joanna Szpadkiewicz",
            "sub": ""
          },
          {
            "text": "Ezequiel Pérez Vázquez",
            "sub": ""
          }
        ]
      }
    },
    "footer": {
      "source": "",
      "page": 59
    }
  }
}