{
  "description": "Create a content slide with a left-side insight headline and a right-side horizontal stacked bar chart showing marquee summer trip booking status by income group.",
  "spec": {
    "slide_type": "content",
    "header": {
      "kicker": "",
      "headline": "In a possible signal of concern about high prices, fewer travelers have fully booked their marquee trips, with the drop most prominent among the $100K to $199K income group",
      "sub": ""
    },
    "layout": "sidebar-right",
    "content": {
      "left": {
        "type": "text-block",
        "title": "",
        "body": ""
      },
      "right": {
        "type": "bar-chart",
        "orientation": "horizontal",
        "series": [
          {
            "name": "2026 average",
            "values": [
              35,
              10,
              7,
              33,
              15
            ]
          },
          {
            "name": "Under $50K",
            "values": [
              24,
              0,
              0,
              0,
              0
            ]
          },
          {
            "name": "$50K to $100K",
            "values": [
              31,
              0,
              0,
              0,
              0
            ]
          },
          {
            "name": "$100K to $199K",
            "values": [
              37,
              0,
              0,
              0,
              0
            ]
          },
          {
            "name": "Over $200K",
            "values": [
              45,
              0,
              0,
              0,
              0
            ]
          }
        ],
        "labels": [
          "Fully booked",
          "Lodging booked, but not transportation",
          "Transportation booked, but not lodging",
          "Destination decided, but no bookings made",
          "Plan to travel, but no destination decision or bookings made"
        ],
        "stacked": true,
        "fmt": "percent",
        "show_values": true,
        "title": "Booking status of marquee summer trips"
      }
    },
    "footer": {
      "source": "2026 Deloitte Summer Travel Survey. Note: Question: “Thinking of the longest trip you will take this summer, how would you describe your progress in planning and booking this trip?” (n = 1,808). Source: 2026 Deloitte Summer Travel Survey.",
      "page": 15
    }
  }
}