{
  "description": "Create a content slide titled 'Insights from ey.com' with a three-column grid of article thumbnails and captions, plus a right sidebar of callout links.",
  "spec": {
    "slide_type": "content",
    "header": {
      "kicker": "Insights: New on ey.com",
      "headline": "Insights from ey.com",
      "sub": "Articles and features on a range of trade issues published on ey.com"
    },
    "layout": "sidebar-right",
    "content": {
      "main": {
        "type": "bullet-list",
        "title": "Featured articles",
        "items": [
          {
            "text": "How AI-led compliance can power India’s export boom",
            "sub": ""
          },
          {
            "text": "Tariff turbulence: 5 actions businesses should take now",
            "sub": ""
          },
          {
            "text": "What the Supreme Court ruling against IEEPA tariffs means in practice",
            "sub": ""
          },
          {
            "text": "How technology is reducing trade finance risk and compliance costs",
            "sub": ""
          }
        ]
      },
      "sidebar": {
        "type": "text-block",
        "title": "Note",
        "body": "For a better viewing experience, please ensure your browser setting is customized to ‘open in a new tab’."
      }
    },
    "footer": {
      "source": "",
      "page": 0
    }
  }
}